{
    "9BB6NFEcjBCtnNLFko2FqVQBq8HHM13kCyYcdQbgpump": {
      "name": "ORCA/USDC",
      "tokenA": "ORCA",
      "tokenB": "USDC",
      "reserveA": 150000,    
      "reserveB":  75000,    
      "decimals": 6,
      "ammId":   "/* optional: Orca pool AMM account pubkey */"
    },
    "9BBayhfBenWrG4wKi6FaFnEe133cLvA4jRmMMc1WiHr3": {
      "name": "ORCA/SOL",
      "tokenA": "ORCA",
      "tokenB": "SOL",
      "reserveA": 200000,    
      "reserveB":   5000,   
      "decimals": 6,
      "ammId":   "/* optional: Orca pool AMM account pubkey */"
    }
  }
  